[{"date": "2023-12-31", "symbol": "HOCN.SW", "reportedCurrency": "CHF", "cik": "0000000000", "fillingDate": "2023-12-31", "acceptedDate": "2023-12-29 19:00:00", "calendarYear": "2023", "period": "FY", "cashAndCashEquivalents": 14556000, "shortTermInvestments": 41879000, "cashAndShortTermInvestments": 14556000, "netReceivables": 49592000, "inventory": 25415000, "otherCurrentAssets": 6572000, "totalCurrentAssets": 96135000, "propertyPlantEquipmentNet": 132116999, "goodwill": 0, "intangibleAssets": 669000, "goodwillAndIntangibleAssets": 669000, "longTermInvestments": 799000, "taxAssets": 0, "otherNonCurrentAssets": 41994001, "totalNonCurrentAssets": 175579000, "otherAssets": 0, "totalAssets": 271714000, "accountPayables": 21225000, "shortTermDebt": 0, "taxPayables": 261000, "deferredRevenue": 0, "otherCurrentLiabilities": 15846000, "totalCurrentLiabilities": 39169000, "longTermDebt": 67000000, "deferredRevenueNonCurrent": 0, "deferredTaxLiabilitiesNonCurrent": 0, "otherNonCurrentLiabilities": 7647000, "totalNonCurrentLiabilities": 74650000, "otherLiabilities": 0, "capitalLeaseObligations": 121000, "totalLiabilities": 113819000, "preferredStock": 0, "commonStock": 21518000, "retainedEarnings": -138156000, "accumulatedOtherComprehensiveIncomeLoss": 0, "othertotalStockholdersEquity": 274850000, "totalStockholdersEquity": 157893000, "totalEquity": 157896000, "totalLiabilitiesAndStockholdersEquity": 271714000, "minorityInterest": 3000, "totalLiabilitiesAndTotalEquity": 271714000, "totalInvestments": 42678000, "totalDebt": 67121000, "netDebt": 52565000, "link": "https://www.six-group.com/en/products-services/the-swiss-stock-exchange.html", "finalLink": "https://www.six-group.com/en/products-services/the-swiss-stock-exchange.html"}, {"date": "2022-12-31", "symbol": "HOCN.SW", "reportedCurrency": "CHF", "cik": "0000000000", "fillingDate": "2022-12-31", "acceptedDate": "2022-12-30 19:00:00", "calendarYear": "2022", "period": "FY", "cashAndCashEquivalents": 10205000, "shortTermInvestments": 223000, "cashAndShortTermInvestments": 10428000, "netReceivables": 52275000, "inventory": 35163000, "otherCurrentAssets": 9630000, "totalCurrentAssets": 107496000, "propertyPlantEquipmentNet": 137712000, "goodwill": 0, "intangibleAssets": 869000, "goodwillAndIntangibleAssets": 869000, "longTermInvestments": 37161000, "taxAssets": 0, "otherNonCurrentAssets": 114000, "totalNonCurrentAssets": 175856000, "otherAssets": 0, "totalAssets": 283352000, "accountPayables": 26851000, "shortTermDebt": 67000000, "taxPayables": 356000, "deferredRevenue": 0, "otherCurrentLiabilities": 13339000, "totalCurrentLiabilities": 108021000, "longTermDebt": 116437000, "deferredRevenueNonCurrent": 121000, "deferredTaxLiabilitiesNonCurrent": 14000, "otherNonCurrentLiabilities": 7461000, "totalNonCurrentLiabilities": 124033000, "otherLiabilities": 0, "capitalLeaseObligations": 121000, "totalLiabilities": 232054000, "preferredStock": 106451000, "commonStock": 21518000, "retainedEarnings": -127969000, "accumulatedOtherComprehensiveIncomeLoss": 35468000, "othertotalStockholdersEquity": 163388000, "totalStockholdersEquity": 51239000, "totalEquity": 51298000, "totalLiabilitiesAndStockholdersEquity": 283352000, "minorityInterest": 59000, "totalLiabilitiesAndTotalEquity": 283352000, "totalInvestments": 37384000, "totalDebt": 183676000, "netDebt": 173471000, "link": "https://www.six-group.com/en/products-services/the-swiss-stock-exchange.html", "finalLink": "https://www.six-group.com/en/products-services/the-swiss-stock-exchange.html"}, {"date": "2021-12-31", "symbol": "HOCN.SW", "reportedCurrency": "CHF", "cik": "0000000000", "fillingDate": "2021-12-31", "acceptedDate": "2021-12-30 19:00:00", "calendarYear": "2021", "period": "FY", "cashAndCashEquivalents": 24285000, "shortTermInvestments": 253000, "cashAndShortTermInvestments": 24538000, "netReceivables": 69144000, "inventory": 31851000, "otherCurrentAssets": 9368000, "totalCurrentAssets": 134901000, "propertyPlantEquipmentNet": 145045000, "goodwill": 0, "intangibleAssets": 1236000, "goodwillAndIntangibleAssets": 1236000, "longTermInvestments": 12045000, "taxAssets": -1, "otherNonCurrentAssets": 113000, "totalNonCurrentAssets": 158438999, "otherAssets": 1, "totalAssets": 293340000, "accountPayables": 25980000, "shortTermDebt": 0, "taxPayables": 149000, "deferredRevenue": 0, "otherCurrentLiabilities": 7753000, "totalCurrentLiabilities": 35335000, "longTermDebt": 173437000, "deferredRevenueNonCurrent": 239000, "deferredTaxLiabilitiesNonCurrent": 8534000, "otherNonCurrentLiabilities": 8966000, "totalNonCurrentLiabilities": 191176000, "otherLiabilities": 0, "capitalLeaseObligations": 239000, "totalLiabilities": 226511000, "preferredStock": 90655000, "commonStock": 21518000, "retainedEarnings": -112173000, "accumulatedOtherComprehensiveIncomeLoss": 52362000, "othertotalStockholdersEquity": 164487000, "totalStockholdersEquity": 66775000, "totalEquity": 66829000, "totalLiabilitiesAndStockholdersEquity": 293340000, "minorityInterest": 54000, "totalLiabilitiesAndTotalEquity": 293340000, "totalInvestments": 12298000, "totalDebt": 173794000, "netDebt": 149509000, "link": "https://www.six-group.com/en/products-services/the-swiss-stock-exchange.html", "finalLink": "https://www.six-group.com/en/products-services/the-swiss-stock-exchange.html"}, {"date": "2020-12-31", "symbol": "HOCN.SW", "reportedCurrency": "CHF", "cik": "0000000000", "fillingDate": "2020-12-31", "acceptedDate": "2020-12-30 19:00:00", "calendarYear": "2020", "period": "FY", "cashAndCashEquivalents": 12411000, "shortTermInvestments": 231000, "cashAndShortTermInvestments": 12642000, "netReceivables": 56239000, "inventory": 29235000, "otherCurrentAssets": 46753000, "totalCurrentAssets": 144869000, "propertyPlantEquipmentNet": 170415000, "goodwill": 0, "intangibleAssets": 1533000, "goodwillAndIntangibleAssets": 1533000, "longTermInvestments": 2964000, "taxAssets": 0, "otherNonCurrentAssets": 4057000, "totalNonCurrentAssets": 178969000, "otherAssets": 0, "totalAssets": 323838000, "accountPayables": 22361000, "shortTermDebt": 0, "taxPayables": 1448000, "deferredRevenue": 0, "otherCurrentLiabilities": 8106000, "totalCurrentLiabilities": 31406000, "longTermDebt": 216437000, "deferredRevenueNonCurrent": 0, "deferredTaxLiabilitiesNonCurrent": 10435000, "otherNonCurrentLiabilities": 1450000, "totalNonCurrentLiabilities": 228322000, "otherLiabilities": 0, "capitalLeaseObligations": 0, "totalLiabilities": 259728000, "preferredStock": 93179000, "commonStock": 21518000, "retainedEarnings": -114697000, "accumulatedOtherComprehensiveIncomeLoss": 49611000, "othertotalStockholdersEquity": 164489000, "totalStockholdersEquity": 64024000, "totalEquity": 64110000, "totalLiabilitiesAndStockholdersEquity": 323838000, "minorityInterest": 86000, "totalLiabilitiesAndTotalEquity": 323838000, "totalInvestments": 3195000, "totalDebt": 216437000, "netDebt": 204026000, "link": "https://www.six-group.com/en/products-services/the-swiss-stock-exchange.html", "finalLink": "https://www.six-group.com/en/products-services/the-swiss-stock-exchange.html"}]