[{"date": "2024-12-31", "symbol": "SCHN.SW", "reportedCurrency": "CHF", "cik": "0000000000", "fillingDate": "2024-12-31", "acceptedDate": "2024-12-31 00:00:00", "calendarYear": "2024", "period": "FY", "cashAndCashEquivalents": 2599000000, "shortTermInvestments": 1466000000, "cashAndShortTermInvestments": 4065000000, "netReceivables": 0, "inventory": 1121000000, "otherCurrentAssets": 2963000000, "totalCurrentAssets": 8288000000, "propertyPlantEquipmentNet": 1368000000, "goodwill": 1064000000, "intangibleAssets": 352000000, "goodwillAndIntangibleAssets": 1416000000, "longTermInvestments": -959000000, "taxAssets": 317000000, "otherNonCurrentAssets": 1567000000, "totalNonCurrentAssets": 3709000000, "otherAssets": 0, "totalAssets": 11997000000, "accountPayables": 1069000000, "shortTermDebt": 209000000, "taxPayables": 378000000, "deferredRevenue": 0, "otherCurrentLiabilities": 3905000000, "totalCurrentLiabilities": 5824000000, "longTermDebt": 92000000, "deferredRevenueNonCurrent": 0, "deferredTaxLiabilitiesNonCurrent": 165000000, "otherNonCurrentLiabilities": 508000000, "totalNonCurrentLiabilities": 1124000000, "otherLiabilities": 0, "capitalLeaseObligations": 493000000, "totalLiabilities": 6948000000, "preferredStock": 0, "commonStock": 11000000, "retainedEarnings": 5945000000, "accumulatedOtherComprehensiveIncomeLoss": 0, "othertotalStockholdersEquity": -1225000000, "totalStockholdersEquity": 4954000000, "totalEquity": 5049000000, "totalLiabilitiesAndStockholdersEquity": 11997000000, "minorityInterest": 95000000, "totalLiabilitiesAndTotalEquity": 11997000000, "totalInvestments": 507000000, "totalDebt": 794000000, "netDebt": -1805000000, "link": "https://www.six-group.com/en/products-services/the-swiss-stock-exchange.html", "finalLink": "https://www.six-group.com/en/products-services/the-swiss-stock-exchange.html"}, {"date": "2023-12-31", "symbol": "SCHN.SW", "reportedCurrency": "CHF", "cik": "0000000000", "fillingDate": "2023-12-31", "acceptedDate": "2023-12-30 19:00:00", "calendarYear": "2023", "period": "FY", "cashAndCashEquivalents": 2336000000, "shortTermInvestments": 1237000000, "cashAndShortTermInvestments": 3573000000, "netReceivables": 2639000000, "inventory": 1251000000, "otherCurrentAssets": 245000000, "totalCurrentAssets": 7824000000, "propertyPlantEquipmentNet": 1327000000, "goodwill": 1033000000, "intangibleAssets": 362000000, "goodwillAndIntangibleAssets": 1395000000, "longTermInvestments": 449000000, "taxAssets": 291000000, "otherNonCurrentAssets": 22000000, "totalNonCurrentAssets": 3484000000, "otherAssets": 0, "totalAssets": 11308000000, "accountPayables": 928000000, "shortTermDebt": 203000000, "taxPayables": 155000000, "deferredRevenue": 2548000000, "otherCurrentLiabilities": 1213000000, "totalCurrentLiabilities": 5594000000, "longTermDebt": 48000000, "deferredRevenueNonCurrent": 0, "deferredTaxLiabilitiesNonCurrent": 141000000, "otherNonCurrentLiabilities": 491000000, "totalNonCurrentLiabilities": 1006000000, "otherLiabilities": 0, "capitalLeaseObligations": 448000000, "totalLiabilities": 6600000000, "preferredStock": 0, "commonStock": 11000000, "retainedEarnings": 5608000000, "accumulatedOtherComprehensiveIncomeLoss": 0, "othertotalStockholdersEquity": -1287000000, "totalStockholdersEquity": 4604000000, "totalEquity": 4708000000, "totalLiabilitiesAndStockholdersEquity": 11308000000, "minorityInterest": 104000000, "totalLiabilitiesAndTotalEquity": 11308000000, "totalInvestments": 1686000000, "totalDebt": 699000000, "netDebt": -1637000000, "link": "https://www.six-group.com/en/products-services/the-swiss-stock-exchange.html", "finalLink": "https://www.six-group.com/en/products-services/the-swiss-stock-exchange.html"}, {"date": "2022-12-31", "symbol": "SCHN.SW", "reportedCurrency": "CHF", "cik": "0000000000", "fillingDate": "2022-12-31", "acceptedDate": "2022-12-30 19:00:00", "calendarYear": "2022", "period": "FY", "cashAndCashEquivalents": 2153000000, "shortTermInvestments": 1287000000, "cashAndShortTermInvestments": 3440000000, "netReceivables": 3146000000, "inventory": 1418000000, "otherCurrentAssets": 301000000, "totalCurrentAssets": 8109000000, "propertyPlantEquipmentNet": 1403000000, "goodwill": 1056000000, "intangibleAssets": 1457000000, "goodwillAndIntangibleAssets": 2513000000, "longTermInvestments": 512000000, "taxAssets": 305000000, "otherNonCurrentAssets": -1034000000, "totalNonCurrentAssets": 3699000000, "otherAssets": 0, "totalAssets": 11808000000, "accountPayables": 957000000, "shortTermDebt": 457000000, "taxPayables": 159000000, "deferredRevenue": 2805000000, "otherCurrentLiabilities": 690000000, "totalCurrentLiabilities": 6252000000, "longTermDebt": 167000000, "deferredRevenueNonCurrent": 24000000, "deferredTaxLiabilitiesNonCurrent": 143000000, "otherNonCurrentLiabilities": 495000000, "totalNonCurrentLiabilities": 1111000000, "otherLiabilities": 0, "capitalLeaseObligations": 306000000, "totalLiabilities": 7363000000, "preferredStock": 1119000000, "commonStock": 11000000, "retainedEarnings": 5182000000, "accumulatedOtherComprehensiveIncomeLoss": -1119000000, "othertotalStockholdersEquity": -2240000000, "totalStockholdersEquity": 4331000000, "totalEquity": 4445000000, "totalLiabilitiesAndStockholdersEquity": 11808000000, "minorityInterest": 114000000, "totalLiabilitiesAndTotalEquity": 11808000000, "totalInvestments": 1799000000, "totalDebt": 1044000000, "netDebt": -1109000000, "link": "https://www.six-group.com/en/products-services/the-swiss-stock-exchange.html", "finalLink": "https://www.six-group.com/en/products-services/the-swiss-stock-exchange.html"}, {"date": "2021-12-31", "symbol": "SCHN.SW", "reportedCurrency": "CHF", "cik": "0000000000", "fillingDate": "2021-12-31", "acceptedDate": "2021-12-30 19:00:00", "calendarYear": "2021", "period": "FY", "cashAndCashEquivalents": 2841000000, "shortTermInvestments": 976000000, "cashAndShortTermInvestments": 3817000000, "netReceivables": 3166000000, "inventory": 1188000000, "otherCurrentAssets": 236000000, "totalCurrentAssets": 8277000000, "propertyPlantEquipmentNet": 1465000000, "goodwill": 986000000, "intangibleAssets": 1389000000, "goodwillAndIntangibleAssets": 2375000000, "longTermInvestments": 530000000, "taxAssets": 291000000, "otherNonCurrentAssets": -964000000, "totalNonCurrentAssets": 3697000000, "otherAssets": 0, "totalAssets": 11974000000, "accountPayables": 928000000, "shortTermDebt": 79000000, "taxPayables": 153000000, "deferredRevenue": 2834000000, "otherCurrentLiabilities": 687000000, "totalCurrentLiabilities": 5955000000, "longTermDebt": 585000000, "deferredRevenueNonCurrent": 443000000, "deferredTaxLiabilitiesNonCurrent": 142000000, "otherNonCurrentLiabilities": 550000000, "totalNonCurrentLiabilities": 1589000000, "otherLiabilities": 0, "capitalLeaseObligations": 312000000, "totalLiabilities": 7544000000, "preferredStock": 1018000000, "commonStock": 11000000, "retainedEarnings": 5028000000, "accumulatedOtherComprehensiveIncomeLoss": -1018000000, "othertotalStockholdersEquity": -2036000000, "totalStockholdersEquity": 4303000000, "totalEquity": 4430000000, "totalLiabilitiesAndStockholdersEquity": 11974000000, "minorityInterest": 127000000, "totalLiabilitiesAndTotalEquity": 11974000000, "totalInvestments": 1506000000, "totalDebt": 1089000000, "netDebt": -1752000000, "link": "https://www.six-group.com/en/products-services/the-swiss-stock-exchange.html", "finalLink": "https://www.six-group.com/en/products-services/the-swiss-stock-exchange.html"}]