[{"date": "2024-12-31", "symbol": "SIKA.SW", "reportedCurrency": "CHF", "cik": "0000000000", "fillingDate": "2024-12-31", "acceptedDate": "2024-12-31 00:00:00", "calendarYear": "2024", "period": "FY", "cashAndCashEquivalents": 707500000, "shortTermInvestments": 5400000, "cashAndShortTermInvestments": 712900000, "netReceivables": 0, "inventory": 1348900000, "otherCurrentAssets": 2501500000, "totalCurrentAssets": 4563300000, "propertyPlantEquipmentNet": 2458500000, "goodwill": 6569400000, "intangibleAssets": 2046700000, "goodwillAndIntangibleAssets": 8616100000, "longTermInvestments": 97900000, "taxAssets": 150700000, "otherNonCurrentAssets": 90700000, "totalNonCurrentAssets": 11413900000, "otherAssets": 0, "totalAssets": 15977200000, "accountPayables": 1212300000, "shortTermDebt": 205800000, "taxPayables": 367700000, "deferredRevenue": 0, "otherCurrentLiabilities": 685900000, "totalCurrentLiabilities": 2585400000, "longTermDebt": 5094600000, "deferredRevenueNonCurrent": 41000000, "deferredTaxLiabilitiesNonCurrent": 338900000, "otherNonCurrentLiabilities": 560900000, "totalNonCurrentLiabilities": 6345000000, "otherLiabilities": 0, "capitalLeaseObligations": 423300000, "totalLiabilities": 8930400000, "preferredStock": 0, "commonStock": 1600000, "retainedEarnings": 5887000000, "accumulatedOtherComprehensiveIncomeLoss": 0, "othertotalStockholdersEquity": -1725300000, "totalStockholdersEquity": 7032800000, "totalEquity": 7046800000, "totalLiabilitiesAndStockholdersEquity": 15977200000, "minorityInterest": 14000000, "totalLiabilitiesAndTotalEquity": 15977200000, "totalInvestments": 103300000, "totalDebt": 5723700000, "netDebt": 5016200000, "link": "https://www.six-group.com/en/products-services/the-swiss-stock-exchange.html", "finalLink": "https://www.six-group.com/en/products-services/the-swiss-stock-exchange.html"}, {"date": "2023-12-31", "symbol": "SIKA.SW", "reportedCurrency": "CHF", "cik": "0000000000", "fillingDate": "2023-12-31", "acceptedDate": "2023-12-30 19:00:00", "calendarYear": "2023", "period": "FY", "cashAndCashEquivalents": 643900000, "shortTermInvestments": 4300000, "cashAndShortTermInvestments": 648200000, "netReceivables": 2021400000, "inventory": 1240700000, "otherCurrentAssets": 47200000, "totalCurrentAssets": 4201300000, "propertyPlantEquipmentNet": 2257300000, "goodwill": 6200400000, "intangibleAssets": 2023200000, "goodwillAndIntangibleAssets": 8223600000, "longTermInvestments": 101400000, "taxAssets": 188600000, "otherNonCurrentAssets": 73000000, "totalNonCurrentAssets": 10843900000, "otherAssets": 5500000, "totalAssets": 15050700000, "accountPayables": 1108200000, "shortTermDebt": 1016900000, "taxPayables": 365400000, "deferredRevenue": 0, "otherCurrentLiabilities": 813500000, "totalCurrentLiabilities": 3416000000, "longTermDebt": 4422200000, "deferredRevenueNonCurrent": 35700000, "deferredTaxLiabilitiesNonCurrent": 402700000, "otherNonCurrentLiabilities": 553900000, "totalNonCurrentLiabilities": 5701500000, "otherLiabilities": 0, "capitalLeaseObligations": 399000000, "totalLiabilities": 9117500000, "preferredStock": 0, "commonStock": 1600000, "retainedEarnings": 4826100000, "accumulatedOtherComprehensiveIncomeLoss": -2038400000, "othertotalStockholdersEquity": 0, "totalStockholdersEquity": 5920400000, "totalEquity": 5933200000, "totalLiabilitiesAndStockholdersEquity": 15050700000, "minorityInterest": 12800000, "totalLiabilitiesAndTotalEquity": 15050700000, "totalInvestments": 105700000, "totalDebt": 5838100000, "netDebt": 5194200000, "link": "https://www.six-group.com/en/products-services/the-swiss-stock-exchange.html", "finalLink": "https://www.six-group.com/en/products-services/the-swiss-stock-exchange.html"}, {"date": "2022-12-31", "symbol": "SIKA.SW", "reportedCurrency": "CHF", "cik": "0000000000", "fillingDate": "2022-12-31", "acceptedDate": "2022-12-30 19:00:00", "calendarYear": "2022", "period": "FY", "cashAndCashEquivalents": 1873300000, "shortTermInvestments": 2800000, "cashAndShortTermInvestments": 1876100000, "netReceivables": 1735500000, "inventory": 1212800000, "otherCurrentAssets": 6800000, "totalCurrentAssets": 5021300000, "propertyPlantEquipmentNet": 1822300000, "goodwill": 3225700000, "intangibleAssets": 4229100000, "goodwillAndIntangibleAssets": 7454800000, "longTermInvestments": 83300000, "taxAssets": 308800000, "otherNonCurrentAssets": -3207300000, "totalNonCurrentAssets": 6461900000, "otherAssets": 0, "totalAssets": 11483200000, "accountPayables": 1016600000, "shortTermDebt": 211000000, "taxPayables": 205900000, "deferredRevenue": 4600000, "otherCurrentLiabilities": 525200000, "totalCurrentLiabilities": 2041400000, "longTermDebt": 3349600000, "deferredRevenueNonCurrent": 36100000, "deferredTaxLiabilitiesNonCurrent": 486500000, "otherNonCurrentLiabilities": 510400000, "totalNonCurrentLiabilities": 4474700000, "otherLiabilities": 0, "capitalLeaseObligations": 256100000, "totalLiabilities": 6516100000, "preferredStock": 0, "commonStock": 1500000, "retainedEarnings": 4333700000, "accumulatedOtherComprehensiveIncomeLoss": -1232700000, "othertotalStockholdersEquity": 0, "totalStockholdersEquity": 4966200000, "totalEquity": 4967100000, "totalLiabilitiesAndStockholdersEquity": 11483200000, "minorityInterest": 900000, "totalLiabilitiesAndTotalEquity": 11483200000, "totalInvestments": 86100000, "totalDebt": 3894800000, "netDebt": 2021500000, "link": "https://www.six-group.com/en/products-services/the-swiss-stock-exchange.html", "finalLink": "https://www.six-group.com/en/products-services/the-swiss-stock-exchange.html"}, {"date": "2021-12-31", "symbol": "SIKA.SW", "reportedCurrency": "CHF", "cik": "0000000000", "fillingDate": "2021-12-31", "acceptedDate": "2021-12-30 19:00:00", "calendarYear": "2021", "period": "FY", "cashAndCashEquivalents": 1175000000, "shortTermInvestments": 4500000, "cashAndShortTermInvestments": 1179500000, "netReceivables": 1587100000, "inventory": 1158300000, "otherCurrentAssets": 50200000, "totalCurrentAssets": 4165500000, "propertyPlantEquipmentNet": 1776600000, "goodwill": 3296600000, "intangibleAssets": 4379900000, "goodwillAndIntangibleAssets": 7676500000, "longTermInvestments": 90800000, "taxAssets": 331500000, "otherNonCurrentAssets": -3144700000, "totalNonCurrentAssets": 6730700000, "otherAssets": 0, "totalAssets": 10896200000, "accountPayables": 1033200000, "shortTermDebt": 216700000, "taxPayables": 170300000, "deferredRevenue": 3900000, "otherCurrentLiabilities": 598599999, "totalCurrentLiabilities": 2096199999, "longTermDebt": 3130400000, "deferredRevenueNonCurrent": 36400000, "deferredTaxLiabilitiesNonCurrent": 555300000, "otherNonCurrentLiabilities": 437900001, "totalNonCurrentLiabilities": 4404100000, "otherLiabilities": 1, "capitalLeaseObligations": 244100000, "totalLiabilities": 6500300000, "preferredStock": 0, "commonStock": 1400000, "retainedEarnings": 4960900000, "accumulatedOtherComprehensiveIncomeLoss": -995200000, "othertotalStockholdersEquity": -995200000, "totalStockholdersEquity": 4393800000, "totalEquity": 4395900000, "totalLiabilitiesAndStockholdersEquity": 10896200000, "minorityInterest": 2100000, "totalLiabilitiesAndTotalEquity": 10896200000, "totalInvestments": 95300000, "totalDebt": 3664700000, "netDebt": 2489700000, "link": "https://www.six-group.com/en/products-services/the-swiss-stock-exchange.html", "finalLink": "https://www.six-group.com/en/products-services/the-swiss-stock-exchange.html"}]