[{"date": "2024-12-31", "symbol": "ZBH.SW", "reportedCurrency": "USD", "cik": "0000000000", "fillingDate": "2024-12-31", "acceptedDate": "2024-12-31 00:00:00", "calendarYear": "2024", "period": "FY", "cashAndCashEquivalents": 525500000, "shortTermInvestments": 0, "cashAndShortTermInvestments": 525500000, "netReceivables": 1480700000, "inventory": 2235300000, "otherCurrentAssets": 430000000, "totalCurrentAssets": 4671500000, "propertyPlantEquipmentNet": 2048800000, "goodwill": 8951100000, "intangibleAssets": 4598400000, "goodwillAndIntangibleAssets": 13549500000, "longTermInvestments": 0, "taxAssets": 0, "otherNonCurrentAssets": 1095500000, "totalNonCurrentAssets": 16693800000, "otherAssets": 0, "totalAssets": 21365300000, "accountPayables": 194600000, "shortTermDebt": 863000000, "taxPayables": 0, "deferredRevenue": 0, "otherCurrentLiabilities": 286000000, "totalCurrentLiabilities": 2450900000, "longTermDebt": 5341600000, "deferredRevenueNonCurrent": 0, "deferredTaxLiabilitiesNonCurrent": 352500000, "otherNonCurrentLiabilities": 744100000, "totalNonCurrentLiabilities": 6438200000, "otherLiabilities": 0, "capitalLeaseObligations": 0, "totalLiabilities": 8889100000, "preferredStock": 0, "commonStock": 3200000, "retainedEarnings": 11095300000, "accumulatedOtherComprehensiveIncomeLoss": -262800000, "othertotalStockholdersEquity": 0, "totalStockholdersEquity": 12468100000, "totalEquity": 12476200000, "totalLiabilitiesAndStockholdersEquity": 21365300000, "minorityInterest": 8100000, "totalLiabilitiesAndTotalEquity": 21365300000, "totalInvestments": 0, "totalDebt": 6204600000, "netDebt": 5679100000, "link": "https://www.six-group.com/en/products-services/the-swiss-stock-exchange.html", "finalLink": "https://www.six-group.com/en/products-services/the-swiss-stock-exchange.html"}, {"date": "2023-12-31", "symbol": "ZBH.SW", "reportedCurrency": "USD", "cik": "0000000000", "fillingDate": "2023-12-31", "acceptedDate": "2023-12-30 19:00:00", "calendarYear": "2023", "period": "FY", "cashAndCashEquivalents": 415800000, "shortTermInvestments": 0, "cashAndShortTermInvestments": 415800000, "netReceivables": 1442400000, "inventory": 2385200000, "otherCurrentAssets": 366100000, "totalCurrentAssets": 4609500000, "propertyPlantEquipmentNet": 2264200000, "goodwill": 8818500000, "intangibleAssets": 4856400000, "goodwillAndIntangibleAssets": 13674900000, "longTermInvestments": 5400000, "taxAssets": 0, "otherNonCurrentAssets": 942900000, "totalNonCurrentAssets": 16887400000, "otherAssets": 0, "totalAssets": 21496900000, "accountPayables": 410600000, "shortTermDebt": 900000000, "taxPayables": 61200000, "deferredRevenue": 0, "otherCurrentLiabilities": 502000000, "totalCurrentLiabilities": 2857400000, "longTermDebt": 5012600000, "deferredRevenueNonCurrent": 0, "deferredTaxLiabilitiesNonCurrent": 0, "otherNonCurrentLiabilities": 1138800000, "totalNonCurrentLiabilities": 6151400000, "otherLiabilities": -100000, "capitalLeaseObligations": 227300000, "totalLiabilities": 9008700000, "preferredStock": 0, "commonStock": 3200000, "retainedEarnings": 10384500000, "accumulatedOtherComprehensiveIncomeLoss": -191000000, "othertotalStockholdersEquity": 0, "totalStockholdersEquity": 12480500000, "totalEquity": 12488200000, "totalLiabilitiesAndStockholdersEquity": 21489300000, "minorityInterest": 7700000, "totalLiabilitiesAndTotalEquity": 21489300000, "totalInvestments": 5400000, "totalDebt": 5912600000, "netDebt": 5496800000, "link": "https://www.six-group.com/en/products-services/the-swiss-stock-exchange.html", "finalLink": "https://www.six-group.com/en/products-services/the-swiss-stock-exchange.html"}, {"date": "2022-12-31", "symbol": "ZBH.SW", "reportedCurrency": "USD", "cik": "0000000000", "fillingDate": "2022-12-31", "acceptedDate": "2022-12-30 19:00:00", "calendarYear": "2022", "period": "FY", "cashAndCashEquivalents": 375700000, "shortTermInvestments": 6800000, "cashAndShortTermInvestments": 375700000, "netReceivables": 1381500000, "inventory": 2147200000, "otherCurrentAssets": 324500000, "totalCurrentAssets": 4427300000, "propertyPlantEquipmentNet": 1872500000, "goodwill": 8580200000, "intangibleAssets": 5063800000, "goodwillAndIntangibleAssets": 13644000000, "longTermInvestments": 0, "taxAssets": 0, "otherNonCurrentAssets": 1122200000, "totalNonCurrentAssets": 16638700000, "otherAssets": 0, "totalAssets": 21066000000, "accountPayables": 354100000, "shortTermDebt": 544300000, "taxPayables": 38500000, "deferredRevenue": 0, "otherCurrentLiabilities": 502800000, "totalCurrentLiabilities": 2358200000, "longTermDebt": 5537800000, "deferredRevenueNonCurrent": 0, "deferredTaxLiabilitiesNonCurrent": 474800000, "otherNonCurrentLiabilities": 1143000000, "totalNonCurrentLiabilities": 6680800000, "otherLiabilities": 0, "capitalLeaseObligations": 220300000, "totalLiabilities": 9039000000, "preferredStock": 0, "commonStock": 3100000, "retainedEarnings": 9559300000, "accumulatedOtherComprehensiveIncomeLoss": -179300000, "othertotalStockholdersEquity": 0, "totalStockholdersEquity": 12021300000, "totalEquity": 12028000000, "totalLiabilitiesAndStockholdersEquity": 21067000000, "minorityInterest": 6700000, "totalLiabilitiesAndTotalEquity": 21067000000, "totalInvestments": 6800000, "totalDebt": 5696500000, "netDebt": 5320800000, "link": "https://www.six-group.com/en/products-services/the-swiss-stock-exchange.html", "finalLink": "https://www.six-group.com/en/products-services/the-swiss-stock-exchange.html"}, {"date": "2021-12-31", "symbol": "ZBH.SW", "reportedCurrency": "USD", "cik": "0000000000", "fillingDate": "2021-12-31", "acceptedDate": "2021-12-30 19:00:00", "calendarYear": "2021", "period": "FY", "cashAndCashEquivalents": 378100000, "shortTermInvestments": 16300000, "cashAndShortTermInvestments": 378100000, "netReceivables": 1259600000, "inventory": 2148000000, "otherCurrentAssets": 772600000, "totalCurrentAssets": 4885000000, "propertyPlantEquipmentNet": 1836600000, "goodwill": 8919400000, "intangibleAssets": 5533600000, "goodwillAndIntangibleAssets": 14453000000, "longTermInvestments": 6700000, "taxAssets": -6700000, "otherNonCurrentAssets": 2281800000, "totalNonCurrentAssets": 18571400000, "otherAssets": 0, "totalAssets": 23456400000, "accountPayables": 306500000, "shortTermDebt": 1605100000, "taxPayables": 62000000, "deferredRevenue": 1045300000, "otherCurrentLiabilities": 640500000, "totalCurrentLiabilities": 3467900000, "longTermDebt": 5652400000, "deferredRevenueNonCurrent": 740900000, "deferredTaxLiabilitiesNonCurrent": 558500000, "otherNonCurrentLiabilities": 928800000, "totalNonCurrentLiabilities": 7322100000, "otherLiabilities": 0, "capitalLeaseObligations": 231600000, "totalLiabilities": 10790000000, "preferredStock": 0, "commonStock": 3100000, "retainedEarnings": 10292200000, "accumulatedOtherComprehensiveIncomeLoss": -231600000, "othertotalStockholdersEquity": 0, "totalStockholdersEquity": 12660700000, "totalEquity": 12666400000, "totalLiabilitiesAndStockholdersEquity": 23456400000, "minorityInterest": 5700000, "totalLiabilitiesAndTotalEquity": 23456400000, "totalInvestments": 23000000, "totalDebt": 7079300000, "netDebt": 6701200000, "link": "https://www.six-group.com/en/products-services/the-swiss-stock-exchange.html", "finalLink": "https://www.six-group.com/en/products-services/the-swiss-stock-exchange.html"}]