[{"date": "2020-12-31", "symbol": "BLS.SW", "reportedCurrency": "CHF", "cik": "0000000000", "fillingDate": "2020-12-31", "acceptedDate": "2020-12-30 19:00:00", "calendarYear": "2020", "period": "FY", "cashAndCashEquivalents": 673477, "shortTermInvestments": 317738, "cashAndShortTermInvestments": 991215, "netReceivables": 0, "inventory": 0, "otherCurrentAssets": 3769655, "totalCurrentAssets": 4760870, "propertyPlantEquipmentNet": 11328867, "goodwill": 77630455, "intangibleAssets": 10824423, "goodwillAndIntangibleAssets": 88454878, "longTermInvestments": 0, "taxAssets": 15506, "otherNonCurrentAssets": 2, "totalNonCurrentAssets": 99799253, "otherAssets": 0, "totalAssets": 104560123, "accountPayables": 639606, "shortTermDebt": 1224914, "taxPayables": 0, "deferredRevenue": 0, "otherCurrentLiabilities": 1028945, "totalCurrentLiabilities": 2893465, "longTermDebt": 12639158, "deferredRevenueNonCurrent": -16688621, "deferredTaxLiabilitiesNonCurrent": 5913983, "otherNonCurrentLiabilities": 16817841, "totalNonCurrentLiabilities": 18682361, "otherLiabilities": 0, "capitalLeaseObligations": 1281514, "totalLiabilities": 21575826, "preferredStock": 0, "commonStock": 21350000, "retainedEarnings": -8318591, "accumulatedOtherComprehensiveIncomeLoss": -1599602, "othertotalStockholdersEquity": 27564024, "totalStockholdersEquity": 38995831, "totalEquity": 38995831, "totalLiabilitiesAndStockholdersEquity": 60571657, "minorityInterest": 0, "totalLiabilitiesAndTotalEquity": 60571657, "totalInvestments": 317738, "totalDebt": 13864072, "netDebt": 13190595, "link": "https://www.six-group.com/en/products-services/the-swiss-stock-exchange.html", "finalLink": "https://www.six-group.com/en/products-services/the-swiss-stock-exchange.html"}, {"date": "2019-12-31", "symbol": "BLS.SW", "reportedCurrency": "CHF", "cik": "0000000000", "fillingDate": "2019-12-31", "acceptedDate": "2019-12-30 19:00:00", "calendarYear": "2019", "period": "FY", "cashAndCashEquivalents": 840829, "shortTermInvestments": 384782, "cashAndShortTermInvestments": 1225611, "netReceivables": 0, "inventory": 0, "otherCurrentAssets": 1157391, "totalCurrentAssets": 2383002, "propertyPlantEquipmentNet": 12641356, "goodwill": 82998665, "intangibleAssets": 12776198, "goodwillAndIntangibleAssets": 95774863, "longTermInvestments": 0, "taxAssets": 8380, "otherNonCurrentAssets": 203607, "totalNonCurrentAssets": 108628206, "otherAssets": 0, "totalAssets": 111011208, "accountPayables": 338784, "shortTermDebt": 207276, "taxPayables": 0, "deferredRevenue": 0, "otherCurrentLiabilities": 767652, "totalCurrentLiabilities": 1313712, "longTermDebt": 29372933, "deferredRevenueNonCurrent": -35994945, "deferredTaxLiabilitiesNonCurrent": 7168072, "otherNonCurrentLiabilities": 36064782, "totalNonCurrentLiabilities": 36610842, "otherLiabilities": 0, "capitalLeaseObligations": 0, "totalLiabilities": 37924554, "preferredStock": 0, "commonStock": 21350000, "retainedEarnings": -22141283, "accumulatedOtherComprehensiveIncomeLoss": -334466, "othertotalStockholdersEquity": 26092035, "totalStockholdersEquity": 24966286, "totalEquity": 24966286, "totalLiabilitiesAndStockholdersEquity": 62890840, "minorityInterest": 0, "totalLiabilitiesAndTotalEquity": 62890840, "totalInvestments": 384782, "totalDebt": 29580209, "netDebt": 28739380, "link": "https://www.six-group.com/en/products-services/the-swiss-stock-exchange.html", "finalLink": "https://www.six-group.com/en/products-services/the-swiss-stock-exchange.html"}, {"date": "2018-12-31", "symbol": "BLS.SW", "reportedCurrency": "CHF", "cik": "0000000000", "fillingDate": "2018-12-31", "acceptedDate": "2018-12-30 19:00:00", "calendarYear": "2018", "period": "FY", "cashAndCashEquivalents": 38870, "shortTermInvestments": 586383, "cashAndShortTermInvestments": 625253, "netReceivables": 0, "inventory": 0, "otherCurrentAssets": 2350522, "totalCurrentAssets": 2975775, "propertyPlantEquipmentNet": 23126209, "goodwill": 0, "intangibleAssets": 0, "goodwillAndIntangibleAssets": 0, "longTermInvestments": 18981381, "taxAssets": 0, "otherNonCurrentAssets": 3234764, "totalNonCurrentAssets": 45342354, "otherAssets": 0, "totalAssets": 48318129, "accountPayables": 229474, "shortTermDebt": 4448859, "taxPayables": 0, "deferredRevenue": 0, "otherCurrentLiabilities": 450695, "totalCurrentLiabilities": 5129028, "longTermDebt": 28326107, "deferredRevenueNonCurrent": 0, "deferredTaxLiabilitiesNonCurrent": 0, "otherNonCurrentLiabilities": 119102, "totalNonCurrentLiabilities": 28445209, "otherLiabilities": 0, "capitalLeaseObligations": 0, "totalLiabilities": 33574237, "preferredStock": 0, "commonStock": 21350000, "retainedEarnings": -29907080, "accumulatedOtherComprehensiveIncomeLoss": 0, "othertotalStockholdersEquity": 23387964, "totalStockholdersEquity": 14830884, "totalEquity": 14830884, "totalLiabilitiesAndStockholdersEquity": 48405121, "minorityInterest": 0, "totalLiabilitiesAndTotalEquity": 48405121, "totalInvestments": 19567764, "totalDebt": 32774966, "netDebt": 32736096, "link": "https://www.six-group.com/en/products-services/the-swiss-stock-exchange.html", "finalLink": "https://www.six-group.com/en/products-services/the-swiss-stock-exchange.html"}, {"date": "2017-12-31", "symbol": "BLS.SW", "reportedCurrency": "CHF", "cik": "0000000000", "fillingDate": "2017-12-31", "acceptedDate": "2017-12-30 19:00:00", "calendarYear": "2017", "period": "FY", "cashAndCashEquivalents": 3720169, "shortTermInvestments": 957541, "cashAndShortTermInvestments": 4677710, "netReceivables": 0, "inventory": 0, "otherCurrentAssets": 567810, "totalCurrentAssets": 5245520, "propertyPlantEquipmentNet": 22860779, "goodwill": 0, "intangibleAssets": 0, "goodwillAndIntangibleAssets": 0, "longTermInvestments": 39099819, "taxAssets": 0, "otherNonCurrentAssets": 1960408, "totalNonCurrentAssets": 63921006, "otherAssets": 0, "totalAssets": 69166526, "accountPayables": 93511, "shortTermDebt": 29530060, "taxPayables": 0, "deferredRevenue": 0, "otherCurrentLiabilities": 222623, "totalCurrentLiabilities": 29846194, "longTermDebt": 3770384, "deferredRevenueNonCurrent": 0, "deferredTaxLiabilitiesNonCurrent": 0, "otherNonCurrentLiabilities": -1, "totalNonCurrentLiabilities": 3770383, "otherLiabilities": 0, "capitalLeaseObligations": 0, "totalLiabilities": 33616577, "preferredStock": 0, "commonStock": 21350000, "retainedEarnings": -7172813, "accumulatedOtherComprehensiveIncomeLoss": 0, "othertotalStockholdersEquity": 21425878, "totalStockholdersEquity": 35603065, "totalEquity": 35603065, "totalLiabilitiesAndStockholdersEquity": 69219642, "minorityInterest": 0, "totalLiabilitiesAndTotalEquity": 69219642, "totalInvestments": 40057360, "totalDebt": 33300444, "netDebt": 29580275, "link": "https://www.six-group.com/en/products-services/the-swiss-stock-exchange.html", "finalLink": "https://www.six-group.com/en/products-services/the-swiss-stock-exchange.html"}]