[{"date": "2024-12-31", "symbol": "EFGN.SW", "reportedCurrency": "CHF", "cik": "0000000000", "fillingDate": "2024-12-31", "acceptedDate": "2024-12-31 00:00:00", "calendarYear": "2024", "period": "FY", "revenue": 1498800000, "costOfRevenue": 0, "grossProfit": 1498800000, "grossProfitRatio": 1, "researchAndDevelopmentExpenses": 0, "generalAndAdministrativeExpenses": 160000000, "sellingAndMarketingExpenses": 14900000, "sellingGeneralAndAdministrativeExpenses": 174900000, "otherExpenses": 1323900000, "operatingExpenses": 1498800000, "costAndExpenses": 1498800000, "interestIncome": 1461300000, "interestExpense": 1078000000, "depreciationAndAmortization": 89300000, "ebitda": 0, "ebitdaratio": 0, "operatingIncome": 0, "operatingIncomeRatio": 0, "totalOtherIncomeExpensesNet": 381400000, "incomeBeforeTax": 381400000, "incomeBeforeTaxRatio": 0.2544702429, "incomeTaxExpense": 59800000, "netIncome": 321600000, "netIncomeRatio": 0.2145716573, "eps": 1, "epsdiluted": 0.95, "weightedAverageShsOut": 301220000, "weightedAverageShsOutDil": 316806000, "link": "https://www.six-group.com/en/products-services/the-swiss-stock-exchange.html", "finalLink": "https://www.six-group.com/en/products-services/the-swiss-stock-exchange.html"}, {"date": "2023-12-31", "symbol": "EFGN.SW", "reportedCurrency": "CHF", "cik": "0000000000", "fillingDate": "2023-12-31", "acceptedDate": "2023-12-30 19:00:00", "calendarYear": "2023", "period": "FY", "revenue": 1430800000, "costOfRevenue": 0, "grossProfit": 1430800000, "grossProfitRatio": 1, "researchAndDevelopmentExpenses": 0, "generalAndAdministrativeExpenses": 152300000, "sellingAndMarketingExpenses": 13000000, "sellingGeneralAndAdministrativeExpenses": 165300000, "otherExpenses": 1265500000, "operatingExpenses": 1430800000, "costAndExpenses": 1430800000, "interestIncome": 1389400000, "interestExpense": 877400000, "depreciationAndAmortization": 78600000, "ebitda": 411800000, "ebitdaratio": 0.2878110148, "operatingIncome": 411800000, "operatingIncomeRatio": 0.2878110148, "totalOtherIncomeExpensesNet": -78600000, "incomeBeforeTax": 333200000, "incomeBeforeTaxRatio": 0.2328767123, "incomeTaxExpense": 30000000, "netIncome": 303200000, "netIncomeRatio": 0.2119094213, "eps": 0.94, "epsdiluted": 0.91, "weightedAverageShsOut": 303138000, "weightedAverageShsOutDil": 311668000, "link": "https://www.six-group.com/en/products-services/the-swiss-stock-exchange.html", "finalLink": "https://www.six-group.com/en/products-services/the-swiss-stock-exchange.html"}, {"date": "2022-12-31", "symbol": "EFGN.SW", "reportedCurrency": "CHF", "cik": "0000000000", "fillingDate": "2022-12-31", "acceptedDate": "2022-12-30 19:00:00", "calendarYear": "2022", "period": "FY", "revenue": 1755700000, "costOfRevenue": 0, "grossProfit": 1755700000, "grossProfitRatio": 1, "researchAndDevelopmentExpenses": 0, "generalAndAdministrativeExpenses": 147900000, "sellingAndMarketingExpenses": 11400000, "sellingGeneralAndAdministrativeExpenses": 41900000, "otherExpenses": -436200000, "operatingExpenses": 436200000, "costAndExpenses": 1449200000, "interestIncome": 678500000, "interestExpense": 48800000, "depreciationAndAmortization": 82700000, "ebitda": 0, "ebitdaratio": -0.0492680982, "operatingIncome": 301800000, "operatingIncomeRatio": 0.171897249, "totalOtherIncomeExpensesNet": -365700000, "incomeBeforeTax": 237100000, "incomeBeforeTaxRatio": 0.1350458507, "incomeTaxExpense": 33400000, "netIncome": 202400000, "netIncomeRatio": 0.115281654, "eps": 0.6, "epsdiluted": 0.57, "weightedAverageShsOut": 305165000, "weightedAverageShsOutDil": 318081000, "link": "https://www.six-group.com/en/products-services/the-swiss-stock-exchange.html", "finalLink": "https://www.six-group.com/en/products-services/the-swiss-stock-exchange.html"}, {"date": "2021-12-31", "symbol": "EFGN.SW", "reportedCurrency": "CHF", "cik": "0000000000", "fillingDate": "2021-12-31", "acceptedDate": "2021-12-30 19:00:00", "calendarYear": "2021", "period": "FY", "revenue": 1634900000, "costOfRevenue": 0, "grossProfit": 1634900000, "grossProfitRatio": 1, "researchAndDevelopmentExpenses": 0, "generalAndAdministrativeExpenses": 139600000, "sellingAndMarketingExpenses": 8900000, "sellingGeneralAndAdministrativeExpenses": 35700000, "otherExpenses": -523500000, "operatingExpenses": 523500000, "costAndExpenses": 1286200000, "interestIncome": 389400000, "interestExpense": 36700000, "depreciationAndAmortization": 82300000, "ebitda": 0, "ebitdaratio": 0.0154749526, "operatingIncome": 192900000, "operatingIncomeRatio": 0.1179888678, "totalOtherIncomeExpensesNet": 52500000, "incomeBeforeTax": 245400000, "incomeBeforeTaxRatio": 0.1501009236, "incomeTaxExpense": 31500000, "netIncome": 205800000, "netIncomeRatio": 0.1258792587, "eps": 0.62, "epsdiluted": 0.59, "weightedAverageShsOut": 299231000, "weightedAverageShsOutDil": 316296000, "link": "https://www.six-group.com/en/products-services/the-swiss-stock-exchange.html", "finalLink": "https://www.six-group.com/en/products-services/the-swiss-stock-exchange.html"}]