[{"date": "2023-12-31", "symbol": "HBLN.SW", "reportedCurrency": "CHF", "cik": "0000000000", "fillingDate": "2023-12-31", "acceptedDate": "2023-12-30 19:00:00", "calendarYear": "2023", "period": "FY", "revenue": 109221000, "costOfRevenue": -30749000, "grossProfit": 139970000, "grossProfitRatio": 1.2815301087, "researchAndDevelopmentExpenses": 0, "generalAndAdministrativeExpenses": 23631000, "sellingAndMarketingExpenses": 49749000, "sellingGeneralAndAdministrativeExpenses": 75700000, "otherExpenses": 0, "operatingExpenses": 75700000, "costAndExpenses": 75700000, "interestIncome": 109252000, "interestExpense": 22810000, "depreciationAndAmortization": 6915000, "ebitda": 6915000, "ebitdaratio": 0.0633120004, "operatingIncome": 30749000, "operatingIncomeRatio": 0.2815301087, "totalOtherIncomeExpensesNet": -6298000, "incomeBeforeTax": 24451000, "incomeBeforeTaxRatio": 0.223867205, "incomeTaxExpense": 3300000, "netIncome": 21150000, "netIncomeRatio": 0.1936440794, "eps": 294.74, "epsdiluted": 294.74, "weightedAverageShsOut": 71759, "weightedAverageShsOutDil": 71759, "link": "https://www.six-group.com/en/products-services/the-swiss-stock-exchange.html", "finalLink": "https://www.six-group.com/en/products-services/the-swiss-stock-exchange.html"}, {"date": "2022-12-31", "symbol": "HBLN.SW", "reportedCurrency": "CHF", "cik": "0000000000", "fillingDate": "2022-12-31", "acceptedDate": "2022-12-30 19:00:00", "calendarYear": "2022", "period": "FY", "revenue": 94953000, "costOfRevenue": 0, "grossProfit": 94953000, "grossProfitRatio": 1, "researchAndDevelopmentExpenses": 0, "generalAndAdministrativeExpenses": 19099000, "sellingAndMarketingExpenses": 43890000, "sellingGeneralAndAdministrativeExpenses": 62989000, "otherExpenses": -23550000, "operatingExpenses": 23550000, "costAndExpenses": 73315000, "interestIncome": 63341000, "interestExpense": 3175000, "depreciationAndAmortization": 4449000, "ebitda": 26087000, "ebitdaratio": 0.0468547597, "operatingIncome": 21638000, "operatingIncomeRatio": 0.2278811623, "totalOtherIncomeExpensesNet": -2887000, "incomeBeforeTax": 21638000, "incomeBeforeTaxRatio": 0.2278811623, "incomeTaxExpense": 3010000, "netIncome": 18628000, "netIncomeRatio": 0.1961812686, "eps": 259.41, "epsdiluted": 259.41, "weightedAverageShsOut": 71809, "weightedAverageShsOutDil": 71809, "link": "https://www.six-group.com/en/products-services/the-swiss-stock-exchange.html", "finalLink": "https://www.six-group.com/en/products-services/the-swiss-stock-exchange.html"}, {"date": "2021-12-31", "symbol": "HBLN.SW", "reportedCurrency": "CHF", "cik": "0000000000", "fillingDate": "2021-12-31", "acceptedDate": "2021-12-30 19:00:00", "calendarYear": "2021", "period": "FY", "revenue": 95694000, "costOfRevenue": 0, "grossProfit": 95694000, "grossProfitRatio": 1, "researchAndDevelopmentExpenses": 0, "generalAndAdministrativeExpenses": 18294000, "sellingAndMarketingExpenses": 50715000, "sellingGeneralAndAdministrativeExpenses": 69009000, "otherExpenses": -21699000, "operatingExpenses": 21699000, "costAndExpenses": 73974000, "interestIncome": 58980000, "interestExpense": 1838000, "depreciationAndAmortization": 14088000, "ebitda": 35808000, "ebitdaratio": 0.1472192614, "operatingIncome": 21720000, "operatingIncomeRatio": 0.226973478, "totalOtherIncomeExpensesNet": -31000, "incomeBeforeTax": 21720000, "incomeBeforeTaxRatio": 0.226973478, "incomeTaxExpense": 3470000, "netIncome": 18250000, "netIncomeRatio": 0.1907120614, "eps": 254.27, "epsdiluted": 254.27, "weightedAverageShsOut": 71775, "weightedAverageShsOutDil": 71775, "link": "https://www.six-group.com/en/products-services/the-swiss-stock-exchange.html", "finalLink": "https://www.six-group.com/en/products-services/the-swiss-stock-exchange.html"}, {"date": "2020-12-31", "symbol": "HBLN.SW", "reportedCurrency": "CHF", "cik": "0000000000", "fillingDate": "2020-12-31", "acceptedDate": "2020-12-30 19:00:00", "calendarYear": "2020", "period": "FY", "revenue": 91865000, "costOfRevenue": 0, "grossProfit": 91865000, "grossProfitRatio": 1, "researchAndDevelopmentExpenses": 0, "generalAndAdministrativeExpenses": 14863000, "sellingAndMarketingExpenses": 48906000, "sellingGeneralAndAdministrativeExpenses": 63769000, "otherExpenses": -16608000, "operatingExpenses": 16608000, "costAndExpenses": 71023000, "interestIncome": 61341000, "interestExpense": 4521000, "depreciationAndAmortization": 12676000, "ebitda": 33518000, "ebitdaratio": 0.1379850868, "operatingIncome": 20842000, "operatingIncomeRatio": 0.2268763947, "totalOtherIncomeExpensesNet": -356000, "incomeBeforeTax": 20842000, "incomeBeforeTaxRatio": 0.2268763947, "incomeTaxExpense": 2765000, "netIncome": 18077000, "netIncomeRatio": 0.1967778806, "eps": 251.61, "epsdiluted": 251.61, "weightedAverageShsOut": 71844, "weightedAverageShsOutDil": 71844, "link": "https://www.six-group.com/en/products-services/the-swiss-stock-exchange.html", "finalLink": "https://www.six-group.com/en/products-services/the-swiss-stock-exchange.html"}]