[{"date": "2024-12-31", "symbol": "MMM.SW", "reportedCurrency": "USD", "cik": "0000000000", "fillingDate": "2024-12-31", "acceptedDate": "2024-12-31 00:00:00", "calendarYear": "2024", "period": "FY", "netIncome": 4188000000, "depreciationAndAmortization": 1363000000, "deferredIncomeTax": 321000000, "stockBasedCompensation": 289000000, "changeInWorkingCapital": -71000000, "accountsReceivables": 114000000, "inventory": 41000000, "accountsPayables": 46000000, "otherWorkingCapital": -272000000, "otherNonCashItems": -4271000000, "netCashProvidedByOperatingActivities": 1819000000, "investmentsInPropertyPlantAndEquipment": -1181000000, "acquisitionsNet": 0, "purchasesOfInvestments": -4153000000, "salesMaturitiesOfInvestments": 2074000000, "otherInvestingActivites": 54000000, "netCashUsedForInvestingActivites": -3206000000, "debtRepayment": 5506000000, "commonStockIssued": 0, "commonStockRepurchased": -1801000000, "dividendsPaid": -1982000000, "otherFinancingActivites": -625000000, "netCashUsedProvidedByFinancingActivities": 1098000000, "effectOfForexChangesOnCash": -44000000, "netChangeInCash": -333000000, "cashAtEndOfPeriod": 5600000000, "cashAtBeginningOfPeriod": 5933000000, "operatingCashFlow": 1819000000, "capitalExpenditure": -1181000000, "freeCashFlow": 638000000, "link": "https://www.six-group.com/en/products-services/the-swiss-stock-exchange.html", "finalLink": "https://www.six-group.com/en/products-services/the-swiss-stock-exchange.html"}, {"date": "2023-12-31", "symbol": "MMM.SW", "reportedCurrency": "USD", "cik": "0000000000", "fillingDate": "2023-12-31", "acceptedDate": "2023-12-30 19:00:00", "calendarYear": "2023", "period": "FY", "netIncome": -6995000000, "depreciationAndAmortization": 1987000000, "deferredIncomeTax": -3855000000, "stockBasedCompensation": 274000000, "changeInWorkingCapital": 317000000, "accountsReceivables": -170000000, "inventory": 567000000, "accountsPayables": 138000000, "otherWorkingCapital": -218000000, "otherNonCashItems": 14952000000, "netCashProvidedByOperatingActivities": 6680000000, "investmentsInPropertyPlantAndEquipment": -1615000000, "acquisitionsNet": 60000000, "purchasesOfInvestments": -1466000000, "salesMaturitiesOfInvestments": 1660000000, "otherInvestingActivites": 154000000, "netCashUsedForInvestingActivites": -1207000000, "debtRepayment": -46000000, "commonStockIssued": 0, "commonStockRepurchased": -33000000, "dividendsPaid": -3311000000, "otherFinancingActivites": 243000000, "netCashUsedProvidedByFinancingActivities": -3147000000, "effectOfForexChangesOnCash": -48000000, "netChangeInCash": 2278000000, "cashAtEndOfPeriod": 5933000000, "cashAtBeginningOfPeriod": 3655000000, "operatingCashFlow": 6680000000, "capitalExpenditure": -1615000000, "freeCashFlow": 5065000000, "link": "https://www.six-group.com/en/products-services/the-swiss-stock-exchange.html", "finalLink": "https://www.six-group.com/en/products-services/the-swiss-stock-exchange.html"}, {"date": "2022-12-31", "symbol": "MMM.SW", "reportedCurrency": "USD", "cik": "0000000000", "fillingDate": "2022-12-31", "acceptedDate": "2022-12-30 19:00:00", "calendarYear": "2022", "period": "FY", "netIncome": 5791000000, "depreciationAndAmortization": 1831000000, "deferredIncomeTax": -663000000, "stockBasedCompensation": 263000000, "changeInWorkingCapital": -670000000, "accountsReceivables": -105000000, "inventory": -629000000, "accountsPayables": 111000000, "otherWorkingCapital": -47000000, "otherNonCashItems": -961000000, "netCashProvidedByOperatingActivities": 5591000000, "investmentsInPropertyPlantAndEquipment": -1749000000, "acquisitionsNet": 491000000, "purchasesOfInvestments": -1250000000, "salesMaturitiesOfInvestments": 1261000000, "otherInvestingActivites": 201000000, "netCashUsedForInvestingActivites": -1046000000, "debtRepayment": -1179000000, "commonStockIssued": 0, "commonStockRepurchased": -1464000000, "dividendsPaid": -3369000000, "otherFinancingActivites": 661000000, "netCashUsedProvidedByFinancingActivities": -5350000000, "effectOfForexChangesOnCash": -104000000, "netChangeInCash": -909000000, "cashAtEndOfPeriod": 3655000000, "cashAtBeginningOfPeriod": 4564000000, "operatingCashFlow": 5591000000, "capitalExpenditure": -1749000000, "freeCashFlow": 3842000000, "link": "https://www.six-group.com/en/products-services/the-swiss-stock-exchange.html", "finalLink": "https://www.six-group.com/en/products-services/the-swiss-stock-exchange.html"}, {"date": "2021-12-31", "symbol": "MMM.SW", "reportedCurrency": "USD", "cik": "0000000000", "fillingDate": "2021-12-31", "acceptedDate": "2021-12-30 19:00:00", "calendarYear": "2021", "period": "FY", "netIncome": 5929000000, "depreciationAndAmortization": 1915000000, "deferredIncomeTax": -166000000, "stockBasedCompensation": 274000000, "changeInWorkingCapital": -751000000, "accountsReceivables": -122000000, "inventory": -903000000, "accountsPayables": 518000000, "otherWorkingCapital": -244000000, "otherNonCashItems": 253000000, "netCashProvidedByOperatingActivities": 7454000000, "investmentsInPropertyPlantAndEquipment": -1603000000, "acquisitionsNet": 0, "purchasesOfInvestments": -2202000000, "salesMaturitiesOfInvestments": 2406000000, "otherInvestingActivites": 82000000, "netCashUsedForInvestingActivites": -1317000000, "debtRepayment": -1144000000, "commonStockIssued": 0, "commonStockRepurchased": -2199000000, "dividendsPaid": -3420000000, "otherFinancingActivites": 619000000, "netCashUsedProvidedByFinancingActivities": -6145000000, "effectOfForexChangesOnCash": -62000000, "netChangeInCash": -70000000, "cashAtEndOfPeriod": 4564000000, "cashAtBeginningOfPeriod": 4634000000, "operatingCashFlow": 7454000000, "capitalExpenditure": -1603000000, "freeCashFlow": 5851000000, "link": "https://www.six-group.com/en/products-services/the-swiss-stock-exchange.html", "finalLink": "https://www.six-group.com/en/products-services/the-swiss-stock-exchange.html"}]