[{"date": "2023-12-31", "symbol": "BCGE.SW", "reportedCurrency": "CHF", "cik": "0000000000", "fillingDate": "2023-12-31", "acceptedDate": "2023-12-29 19:00:00", "calendarYear": "2023", "period": "FY", "netIncome": 231240000, "depreciationAndAmortization": 20332000, "deferredIncomeTax": 0, "stockBasedCompensation": 0, "changeInWorkingCapital": -140332000, "accountsReceivables": 0, "inventory": 0, "accountsPayables": 0, "otherWorkingCapital": -140332000, "otherNonCashItems": 281954000, "netCashProvidedByOperatingActivities": 393194000, "investmentsInPropertyPlantAndEquipment": -26069000, "acquisitionsNet": 0, "purchasesOfInvestments": 0, "salesMaturitiesOfInvestments": 0, "otherInvestingActivites": -329025000, "netCashUsedForInvestingActivites": -355094000, "debtRepayment": -745479000, "commonStockIssued": 0, "commonStockRepurchased": 0, "dividendsPaid": -7920000, "otherFinancingActivites": 1000444000, "netCashUsedProvidedByFinancingActivities": -43798000, "effectOfForexChangesOnCash": 0, "netChangeInCash": 5698000, "cashAtEndOfPeriod": 207232000, "cashAtBeginningOfPeriod": 201534000, "operatingCashFlow": 393194000, "capitalExpenditure": -26069000, "freeCashFlow": 367125000, "link": "https://www.six-group.com/en/products-services/the-swiss-stock-exchange.html", "finalLink": "https://www.six-group.com/en/products-services/the-swiss-stock-exchange.html"}, {"date": "2022-12-31", "symbol": "BCGE.SW", "reportedCurrency": "CHF", "cik": "0000000000", "fillingDate": "2022-12-31", "acceptedDate": "2022-12-30 19:00:00", "calendarYear": "2022", "period": "FY", "netIncome": 175888000, "depreciationAndAmortization": 18717000, "deferredIncomeTax": 0, "stockBasedCompensation": 0, "changeInWorkingCapital": -473563000, "accountsReceivables": 0, "inventory": 0, "accountsPayables": 0, "otherWorkingCapital": -473563000, "otherNonCashItems": 309984000, "netCashProvidedByOperatingActivities": 31026000, "investmentsInPropertyPlantAndEquipment": -17979000, "acquisitionsNet": -5156000, "purchasesOfInvestments": -107965000, "salesMaturitiesOfInvestments": 3602000, "otherInvestingActivites": -793595000, "netCashUsedForInvestingActivites": -921093000, "debtRepayment": -68490000, "commonStockIssued": 0, "commonStockRepurchased": 0, "dividendsPaid": -6480000, "otherFinancingActivites": -218680000, "netCashUsedProvidedByFinancingActivities": 1137803000, "effectOfForexChangesOnCash": -469594000, "netChangeInCash": -221858000, "cashAtEndOfPeriod": 247736000, "cashAtBeginningOfPeriod": 469594000, "operatingCashFlow": 31026000, "capitalExpenditure": -17979000, "freeCashFlow": 13047000, "link": "https://www.six-group.com/en/products-services/the-swiss-stock-exchange.html", "finalLink": "https://www.six-group.com/en/products-services/the-swiss-stock-exchange.html"}, {"date": "2021-12-31", "symbol": "BCGE.SW", "reportedCurrency": "CHF", "cik": "0000000000", "fillingDate": "2021-12-31", "acceptedDate": "2021-12-30 19:00:00", "calendarYear": "2021", "period": "FY", "netIncome": 125213000, "depreciationAndAmortization": 16847000, "deferredIncomeTax": 0, "stockBasedCompensation": 0, "changeInWorkingCapital": -102454000, "accountsReceivables": 0, "inventory": 0, "accountsPayables": 0, "otherWorkingCapital": -102454000, "otherNonCashItems": 88166000, "netCashProvidedByOperatingActivities": 127772000, "investmentsInPropertyPlantAndEquipment": -24849000, "acquisitionsNet": -11096000, "purchasesOfInvestments": -15225000, "salesMaturitiesOfInvestments": 121701000, "otherInvestingActivites": -806861000, "netCashUsedForInvestingActivites": -736330000, "debtRepayment": -740119000, "commonStockIssued": 2545000, "commonStockRepurchased": 0, "dividendsPaid": -5400000, "otherFinancingActivites": 1345135000, "netCashUsedProvidedByFinancingActivities": 602161000, "effectOfForexChangesOnCash": 0, "netChangeInCash": -6397000, "cashAtEndOfPeriod": -6397000, "cashAtBeginningOfPeriod": 0, "operatingCashFlow": 127772000, "capitalExpenditure": -24849000, "freeCashFlow": 102923000, "link": "https://www.six-group.com/en/products-services/the-swiss-stock-exchange.html", "finalLink": "https://www.six-group.com/en/products-services/the-swiss-stock-exchange.html"}, {"date": "2020-12-31", "symbol": "BCGE.SW", "reportedCurrency": "CHF", "cik": "0000000000", "fillingDate": "2020-12-31", "acceptedDate": "2020-12-30 19:00:00", "calendarYear": "2020", "period": "FY", "netIncome": 104974000, "depreciationAndAmortization": 15285000, "deferredIncomeTax": 0, "stockBasedCompensation": 0, "changeInWorkingCapital": -236089000, "accountsReceivables": 0, "inventory": 0, "accountsPayables": 0, "otherWorkingCapital": -236089000, "otherNonCashItems": -87867000, "netCashProvidedByOperatingActivities": -203697000, "investmentsInPropertyPlantAndEquipment": -11289000, "acquisitionsNet": 6520000, "purchasesOfInvestments": -261317999, "salesMaturitiesOfInvestments": 11076000, "otherInvestingActivites": -592115001, "netCashUsedForInvestingActivites": -847126000, "debtRepayment": -856665000, "commonStockIssued": 0, "commonStockRepurchased": -8239000, "dividendsPaid": -5400000, "otherFinancingActivites": -1178075000, "netCashUsedProvidedByFinancingActivities": 2779073000, "effectOfForexChangesOnCash": 0, "netChangeInCash": 1728250000, "cashAtEndOfPeriod": 6474360000, "cashAtBeginningOfPeriod": 4746110000, "operatingCashFlow": -203697000, "capitalExpenditure": -11289000, "freeCashFlow": -214986000, "link": "https://www.six-group.com/en/products-services/the-swiss-stock-exchange.html", "finalLink": "https://www.six-group.com/en/products-services/the-swiss-stock-exchange.html"}]