[{"date": "2024-12-31", "symbol": "VACN.SW", "reportedCurrency": "CHF", "cik": "0000000000", "fillingDate": "2024-12-31", "acceptedDate": "2024-12-31 00:00:00", "calendarYear": "2024", "period": "FY", "netIncome": 211799000, "depreciationAndAmortization": 43487000, "deferredIncomeTax": 0, "stockBasedCompensation": 0, "changeInWorkingCapital": -31840000, "accountsReceivables": -29571000, "inventory": -49866000, "accountsPayables": 0, "otherWorkingCapital": 47597000, "otherNonCashItems": 17196000, "netCashProvidedByOperatingActivities": 240642000, "investmentsInPropertyPlantAndEquipment": -46646000, "acquisitionsNet": 0, "purchasesOfInvestments": 0, "salesMaturitiesOfInvestments": 0, "otherInvestingActivites": -10748000, "netCashUsedForInvestingActivites": -57394000, "debtRepayment": 30000000, "commonStockIssued": 0, "commonStockRepurchased": -7019000, "dividendsPaid": -187415000, "otherFinancingActivites": -8066000, "netCashUsedProvidedByFinancingActivities": -172500000, "effectOfForexChangesOnCash": 3267000, "netChangeInCash": 14013000, "cashAtEndOfPeriod": 158121000, "cashAtBeginningOfPeriod": 144108000, "operatingCashFlow": 240642000, "capitalExpenditure": -55668000, "freeCashFlow": 184974000, "link": "https://www.six-group.com/en/products-services/the-swiss-stock-exchange.html", "finalLink": "https://www.six-group.com/en/products-services/the-swiss-stock-exchange.html"}, {"date": "2023-12-31", "symbol": "VACN.SW", "reportedCurrency": "CHF", "cik": "0000000000", "fillingDate": "2023-12-31", "acceptedDate": "2023-12-29 19:00:00", "calendarYear": "2023", "period": "FY", "netIncome": 190310000, "depreciationAndAmortization": 41359000, "deferredIncomeTax": 0, "stockBasedCompensation": 0, "changeInWorkingCapital": 20836000, "accountsReceivables": 42833000, "inventory": 25859000, "accountsPayables": -49565000, "otherWorkingCapital": 1709000, "otherNonCashItems": 3901000, "netCashProvidedByOperatingActivities": 256406000, "investmentsInPropertyPlantAndEquipment": -60267000, "acquisitionsNet": 0, "purchasesOfInvestments": 0, "salesMaturitiesOfInvestments": 0, "otherInvestingActivites": -7381000, "netCashUsedForInvestingActivites": -67648000, "debtRepayment": -310000000, "commonStockIssued": 0, "commonStockRepurchased": -5742000, "dividendsPaid": -187436000, "otherFinancingActivites": -12405000, "netCashUsedProvidedByFinancingActivities": -205583000, "effectOfForexChangesOnCash": -13432000, "netChangeInCash": -30257000, "cashAtEndOfPeriod": 144108000, "cashAtBeginningOfPeriod": 174365000, "operatingCashFlow": 256406000, "capitalExpenditure": -69236000, "freeCashFlow": 187170000, "link": "https://www.six-group.com/en/products-services/the-swiss-stock-exchange.html", "finalLink": "https://www.six-group.com/en/products-services/the-swiss-stock-exchange.html"}, {"date": "2022-12-31", "symbol": "VACN.SW", "reportedCurrency": "CHF", "cik": "0000000000", "fillingDate": "2022-12-31", "acceptedDate": "2022-12-30 19:00:00", "calendarYear": "2022", "period": "FY", "netIncome": 306779000, "depreciationAndAmortization": 40969000, "deferredIncomeTax": -3278000, "stockBasedCompensation": 2177000, "changeInWorkingCapital": -77466000, "accountsReceivables": -43831000, "inventory": -81035000, "accountsPayables": 54587000, "otherWorkingCapital": -7187000, "otherNonCashItems": 20556000, "netCashProvidedByOperatingActivities": 289737000, "investmentsInPropertyPlantAndEquipment": -66239999, "acquisitionsNet": 17000, "purchasesOfInvestments": 0, "salesMaturitiesOfInvestments": 0, "otherInvestingActivites": -1, "netCashUsedForInvestingActivites": -66223000, "debtRepayment": -1000, "commonStockIssued": 0, "commonStockRepurchased": -4459000, "dividendsPaid": -164957000, "otherFinancingActivites": -7822000, "netCashUsedProvidedByFinancingActivities": -172581000, "effectOfForexChangesOnCash": -3720000, "netChangeInCash": 47213000, "cashAtEndOfPeriod": 174365000, "cashAtBeginningOfPeriod": 127152000, "operatingCashFlow": 289737000, "capitalExpenditure": -66239999, "freeCashFlow": 223497001, "link": "https://www.six-group.com/en/products-services/the-swiss-stock-exchange.html", "finalLink": "https://www.six-group.com/en/products-services/the-swiss-stock-exchange.html"}, {"date": "2021-12-31", "symbol": "VACN.SW", "reportedCurrency": "CHF", "cik": "0000000000", "fillingDate": "2021-12-31", "acceptedDate": "2021-12-30 19:00:00", "calendarYear": "2021", "period": "FY", "netIncome": 217440000, "depreciationAndAmortization": 43058000, "deferredIncomeTax": 1833000, "stockBasedCompensation": 1960000, "changeInWorkingCapital": -40138000, "accountsReceivables": -31143000, "inventory": -47779000, "accountsPayables": 33408000, "otherWorkingCapital": 5376000, "otherNonCashItems": 10819000, "netCashProvidedByOperatingActivities": 234972000, "investmentsInPropertyPlantAndEquipment": -42967000, "acquisitionsNet": -1259000, "purchasesOfInvestments": 0, "salesMaturitiesOfInvestments": 0, "otherInvestingActivites": -10084001, "netCashUsedForInvestingActivites": -44226000, "debtRepayment": -59999000, "commonStockIssued": 0, "commonStockRepurchased": -4344000, "dividendsPaid": -134982000, "otherFinancingActivites": -7381000, "netCashUsedProvidedByFinancingActivities": -201758000, "effectOfForexChangesOnCash": 292000, "netChangeInCash": -10719000, "cashAtEndOfPeriod": 127152000, "cashAtBeginningOfPeriod": 137871000, "operatingCashFlow": 234972000, "capitalExpenditure": -42967000, "freeCashFlow": 192005000, "link": "https://www.six-group.com/en/products-services/the-swiss-stock-exchange.html", "finalLink": "https://www.six-group.com/en/products-services/the-swiss-stock-exchange.html"}]